{"nodes": [{"id": "e_attendence_vendors_aspx_cs", "label": "Vendors.aspx.cs", "file_type": "code", "source_file": "Vendors.aspx.cs", "source_location": "L1"}, {"id": "attendence_vendors_aspx_attendanceapp", "label": "AttendanceApp", "file_type": "code", "source_file": "Vendors.aspx.cs", "source_location": "L9"}, {"id": "attendence_vendors_aspx_vendors", "label": "Vendors", "file_type": "code", "source_file": "Vendors.aspx.cs", "source_location": "L11"}, {"id": "page", "label": "Page", "file_type": "code", "source_file": "", "source_location": ""}, {"id": "attendence_vendors_aspx_vendors_page_load", "label": ".Page_Load()", "file_type": "code", "source_file": "Vendors.aspx.cs", "source_location": "L13"}, {"id": "eventargs", "label": "EventArgs", "file_type": "code", "source_file": "Vendors.aspx.cs", "source_location": "L13"}, {"id": "attendence_vendors_aspx_vendors_bindgrid", "label": ".BindGrid()", "file_type": "code", "source_file": "Vendors.aspx.cs", "source_location": "L37"}, {"id": "attendence_vendors_aspx_vendors_btnsearch_click", "label": ".btnSearch_Click()", "file_type": "code", "source_file": "Vendors.aspx.cs", "source_location": "L69"}, {"id": "attendence_vendors_aspx_vendors_btnsave_click", "label": ".btnSave_Click()", "file_type": "code", "source_file": "Vendors.aspx.cs", "source_location": "L74"}, {"id": "attendence_vendors_aspx_vendors_btncancel_click", "label": ".btnCancel_Click()", "file_type": "code", "source_file": "Vendors.aspx.cs", "source_location": "L174"}, {"id": "attendence_vendors_aspx_vendors_gvvendors_rowcommand", "label": ".gvVendors_RowCommand()", "file_type": "code", "source_file": "Vendors.aspx.cs", "source_location": "L180"}, {"id": "gridviewcommandeventargs", "label": "GridViewCommandEventArgs", "file_type": "code", "source_file": "Vendors.aspx.cs", "source_location": "L180"}, {"id": "attendence_vendors_aspx_vendors_resetform", "label": ".ResetForm()", "file_type": "code", "source_file": "Vendors.aspx.cs", "source_location": "L230"}, {"id": "attendence_vendors_aspx_vendors_btnhiddenedittrigger_click", "label": ".btnHiddenEditTrigger_Click()", "file_type": "code", "source_file": "Vendors.aspx.cs", "source_location": "L247"}, {"id": "attendence_vendors_aspx_vendors_loadvendorforedit", "label": ".LoadVendorForEdit()", "file_type": "code", "source_file": "Vendors.aspx.cs", "source_location": "L257"}, {"id": "attendence_vendors_aspx_vendors_openhistorymodal", "label": ".OpenHistoryModal()", "file_type": "code", "source_file": "Vendors.aspx.cs", "source_location": "L289"}, {"id": "attendence_vendors_aspx_vendors_escapejs", "label": ".EscapeJs()", "file_type": "code", "source_file": "Vendors.aspx.cs", "source_location": "L367"}, {"id": "attendence_vendors_aspx_vendors_generatenextmasterid", "label": ".GenerateNextMasterId()", "file_type": "code", "source_file": "Vendors.aspx.cs", "source_location": "L374"}, {"id": "attendence_vendors_aspx_vendors_showmessage", "label": ".ShowMessage()", "file_type": "code", "source_file": "Vendors.aspx.cs", "source_location": "L401"}], "edges": [{"source": "e_attendence_vendors_aspx_cs", "target": "system", "relation": "imports", "context": "import", "confidence": "EXTRACTED", "source_file": "Vendors.aspx.cs", "source_location": "L1", "weight": 1.0}, {"source": "e_attendence_vendors_aspx_cs", "target": "generic", "relation": "imports", "context": "import", "confidence": "EXTRACTED", "source_file": "Vendors.aspx.cs", "source_location": "L2", "weight": 1.0}, {"source": "e_attendence_vendors_aspx_cs", "target": "data", "relation": "imports", "context": "import", "confidence": "EXTRACTED", "source_file": "Vendors.aspx.cs", "source_location": "L3", "weight": 1.0}, {"source": "e_attendence_vendors_aspx_cs", "target": "ui", "relation": "imports", "context": "import", "confidence": "EXTRACTED", "source_file": "Vendors.aspx.cs", "source_location": "L4", "weight": 1.0}, {"source": "e_attendence_vendors_aspx_cs", "target": "webcontrols", "relation": "imports", "context": "import", "confidence": "EXTRACTED", "source_file": "Vendors.aspx.cs", "source_location": "L5", "weight": 1.0}, {"source": "e_attendence_vendors_aspx_cs", "target": "utils", "relation": "imports", "context": "import", "confidence": "EXTRACTED", "source_file": "Vendors.aspx.cs", "source_location": "L6", "weight": 1.0}, {"source": "e_attendence_vendors_aspx_cs", "target": "client", "relation": "imports", "context": "import", "confidence": "EXTRACTED", "source_file": "Vendors.aspx.cs", "source_location": "L7", "weight": 1.0}, {"source": "e_attendence_vendors_aspx_cs", "target": "attendence_vendors_aspx_attendanceapp", "relation": "contains", "confidence": "EXTRACTED", "source_file": "Vendors.aspx.cs", "source_location": "L9", "weight": 1.0}, {"source": "e_attendence_vendors_aspx_cs", "target": "attendence_vendors_aspx_vendors", "relation": "contains", "confidence": "EXTRACTED", "source_file": "Vendors.aspx.cs", "source_location": "L11", "weight": 1.0}, {"source": "attendence_vendors_aspx_vendors", "target": "page", "relation": "inherits", "confidence": "EXTRACTED", "source_file": "Vendors.aspx.cs", "source_location": "L11", "weight": 1.0}, {"source": "attendence_vendors_aspx_vendors", "target": "attendence_vendors_aspx_vendors_page_load", "relation": "method", "confidence": "EXTRACTED", "source_file": "Vendors.aspx.cs", "source_location": "L13", "weight": 1.0}, {"source": "attendence_vendors_aspx_vendors_page_load", "target": "eventargs", "relation": "references", "confidence": "EXTRACTED", "source_file": "Vendors.aspx.cs", "source_location": "L13", "weight": 1.0, "context": "parameter_type"}, {"source": "attendence_vendors_aspx_vendors", "target": "attendence_vendors_aspx_vendors_bindgrid", "relation": "method", "confidence": "EXTRACTED", "source_file": "Vendors.aspx.cs", "source_location": "L37", "weight": 1.0}, {"source": "attendence_vendors_aspx_vendors", "target": "attendence_vendors_aspx_vendors_btnsearch_click", "relation": "method", "confidence": "EXTRACTED", "source_file": "Vendors.aspx.cs", "source_location": "L69", "weight": 1.0}, {"source": "attendence_vendors_aspx_vendors_btnsearch_click", "target": "eventargs", "relation": "references", "confidence": "EXTRACTED", "source_file": "Vendors.aspx.cs", "source_location": "L69", "weight": 1.0, "context": "parameter_type"}, {"source": "attendence_vendors_aspx_vendors", "target": "attendence_vendors_aspx_vendors_btnsave_click", "relation": "method", "confidence": "EXTRACTED", "source_file": "Vendors.aspx.cs", "source_location": "L74", "weight": 1.0}, {"source": "attendence_vendors_aspx_vendors_btnsave_click", "target": "eventargs", "relation": "references", "confidence": "EXTRACTED", "source_file": "Vendors.aspx.cs", "source_location": "L74", "weight": 1.0, "context": "parameter_type"}, {"source": "attendence_vendors_aspx_vendors", "target": "attendence_vendors_aspx_vendors_btncancel_click", "relation": "method", "confidence": "EXTRACTED", "source_file": "Vendors.aspx.cs", "source_location": "L174", "weight": 1.0}, {"source": "attendence_vendors_aspx_vendors_btncancel_click", "target": "eventargs", "relation": "references", "confidence": "EXTRACTED", "source_file": "Vendors.aspx.cs", "source_location": "L174", "weight": 1.0, "context": "parameter_type"}, {"source": "attendence_vendors_aspx_vendors", "target": "attendence_vendors_aspx_vendors_gvvendors_rowcommand", "relation": "method", "confidence": "EXTRACTED", "source_file": "Vendors.aspx.cs", "source_location": "L180", "weight": 1.0}, {"source": "attendence_vendors_aspx_vendors_gvvendors_rowcommand", "target": "gridviewcommandeventargs", "relation": "references", "confidence": "EXTRACTED", "source_file": "Vendors.aspx.cs", "source_location": "L180", "weight": 1.0, "context": "parameter_type"}, {"source": "attendence_vendors_aspx_vendors", "target": "attendence_vendors_aspx_vendors_resetform", "relation": "method", "confidence": "EXTRACTED", "source_file": "Vendors.aspx.cs", "source_location": "L230", "weight": 1.0}, {"source": "attendence_vendors_aspx_vendors", "target": "attendence_vendors_aspx_vendors_btnhiddenedittrigger_click", "relation": "method", "confidence": "EXTRACTED", "source_file": "Vendors.aspx.cs", "source_location": "L247", "weight": 1.0}, {"source": "attendence_vendors_aspx_vendors_btnhiddenedittrigger_click", "target": "eventargs", "relation": "references", "confidence": "EXTRACTED", "source_file": "Vendors.aspx.cs", "source_location": "L247", "weight": 1.0, "context": "parameter_type"}, {"source": "attendence_vendors_aspx_vendors", "target": "attendence_vendors_aspx_vendors_loadvendorforedit", "relation": "method", "confidence": "EXTRACTED", "source_file": "Vendors.aspx.cs", "source_location": "L257", "weight": 1.0}, {"source": "attendence_vendors_aspx_vendors", "target": "attendence_vendors_aspx_vendors_openhistorymodal", "relation": "method", "confidence": "EXTRACTED", "source_file": "Vendors.aspx.cs", "source_location": "L289", "weight": 1.0}, {"source": "attendence_vendors_aspx_vendors", "target": "attendence_vendors_aspx_vendors_escapejs", "relation": "method", "confidence": "EXTRACTED", "source_file": "Vendors.aspx.cs", "source_location": "L367", "weight": 1.0}, {"source": "attendence_vendors_aspx_vendors", "target": "attendence_vendors_aspx_vendors_generatenextmasterid", "relation": "method", "confidence": "EXTRACTED", "source_file": "Vendors.aspx.cs", "source_location": "L374", "weight": 1.0}, {"source": "attendence_vendors_aspx_vendors", "target": "attendence_vendors_aspx_vendors_showmessage", "relation": "method", "confidence": "EXTRACTED", "source_file": "Vendors.aspx.cs", "source_location": "L401", "weight": 1.0}, {"source": "attendence_vendors_aspx_vendors", "target": "attendence_vendors_aspx_vendors_showmessage", "relation": "method", "confidence": "EXTRACTED", "source_file": "Vendors.aspx.cs", "source_location": "L406", "weight": 1.0}, {"source": "attendence_vendors_aspx_vendors_page_load", "target": "attendence_vendors_aspx_vendors_bindgrid", "relation": "calls", "context": "call", "confidence": "EXTRACTED", "source_file": "Vendors.aspx.cs", "source_location": "L32", "weight": 1.0}, {"source": "attendence_vendors_aspx_vendors_bindgrid", "target": "attendence_vendors_aspx_vendors_showmessage", "relation": "calls", "context": "call", "confidence": "EXTRACTED", "source_file": "Vendors.aspx.cs", "source_location": "L65", "weight": 1.0}, {"source": "attendence_vendors_aspx_vendors_btnsearch_click", "target": "attendence_vendors_aspx_vendors_bindgrid", "relation": "calls", "context": "call", "confidence": "EXTRACTED", "source_file": "Vendors.aspx.cs", "source_location": "L71", "weight": 1.0}, {"source": "attendence_vendors_aspx_vendors_btnsave_click", "target": "attendence_vendors_aspx_vendors_showmessage", "relation": "calls", "context": "call", "confidence": "EXTRACTED", "source_file": "Vendors.aspx.cs", "source_location": "L85", "weight": 1.0}, {"source": "attendence_vendors_aspx_vendors_btnsave_click", "target": "attendence_vendors_aspx_vendors_generatenextmasterid", "relation": "calls", "context": "call", "confidence": "EXTRACTED", "source_file": "Vendors.aspx.cs", "source_location": "L96", "weight": 1.0}, {"source": "attendence_vendors_aspx_vendors_btnsave_click", "target": "attendence_vendors_aspx_vendors_resetform", "relation": "calls", "context": "call", "confidence": "EXTRACTED", "source_file": "Vendors.aspx.cs", "source_location": "L165", "weight": 1.0}, {"source": "attendence_vendors_aspx_vendors_btnsave_click", "target": "attendence_vendors_aspx_vendors_bindgrid", "relation": "calls", "context": "call", "confidence": "EXTRACTED", "source_file": "Vendors.aspx.cs", "source_location": "L166", "weight": 1.0}, {"source": "attendence_vendors_aspx_vendors_btncancel_click", "target": "attendence_vendors_aspx_vendors_resetform", "relation": "calls", "context": "call", "confidence": "EXTRACTED", "source_file": "Vendors.aspx.cs", "source_location": "L176", "weight": 1.0}, {"source": "attendence_vendors_aspx_vendors_btncancel_click", "target": "attendence_vendors_aspx_vendors_showmessage", "relation": "calls", "context": "call", "confidence": "EXTRACTED", "source_file": "Vendors.aspx.cs", "source_location": "L177", "weight": 1.0}, {"source": "attendence_vendors_aspx_vendors_gvvendors_rowcommand", "target": "attendence_vendors_aspx_vendors_loadvendorforedit", "relation": "calls", "context": "call", "confidence": "EXTRACTED", "source_file": "Vendors.aspx.cs", "source_location": "L185", "weight": 1.0}, {"source": "attendence_vendors_aspx_vendors_gvvendors_rowcommand", "target": "attendence_vendors_aspx_vendors_openhistorymodal", "relation": "calls", "context": "call", "confidence": "EXTRACTED", "source_file": "Vendors.aspx.cs", "source_location": "L190", "weight": 1.0}, {"source": "attendence_vendors_aspx_vendors_gvvendors_rowcommand", "target": "attendence_vendors_aspx_vendors_showmessage", "relation": "calls", "context": "call", "confidence": "EXTRACTED", "source_file": "Vendors.aspx.cs", "source_location": "L210", "weight": 1.0}, {"source": "attendence_vendors_aspx_vendors_gvvendors_rowcommand", "target": "attendence_vendors_aspx_vendors_resetform", "relation": "calls", "context": "call", "confidence": "EXTRACTED", "source_file": "Vendors.aspx.cs", "source_location": "L220", "weight": 1.0}, {"source": "attendence_vendors_aspx_vendors_gvvendors_rowcommand", "target": "attendence_vendors_aspx_vendors_bindgrid", "relation": "calls", "context": "call", "confidence": "EXTRACTED", "source_file": "Vendors.aspx.cs", "source_location": "L221", "weight": 1.0}, {"source": "attendence_vendors_aspx_vendors_btnhiddenedittrigger_click", "target": "attendence_vendors_aspx_vendors_loadvendorforedit", "relation": "calls", "context": "call", "confidence": "EXTRACTED", "source_file": "Vendors.aspx.cs", "source_location": "L253", "weight": 1.0}, {"source": "attendence_vendors_aspx_vendors_loadvendorforedit", "target": "attendence_vendors_aspx_vendors_showmessage", "relation": "calls", "context": "call", "confidence": "EXTRACTED", "source_file": "Vendors.aspx.cs", "source_location": "L280", "weight": 1.0}, {"source": "attendence_vendors_aspx_vendors_openhistorymodal", "target": "attendence_vendors_aspx_vendors_showmessage", "relation": "calls", "context": "call", "confidence": "EXTRACTED", "source_file": "Vendors.aspx.cs", "source_location": "L304", "weight": 1.0}, {"source": "attendence_vendors_aspx_vendors_openhistorymodal", "target": "attendence_vendors_aspx_vendors_escapejs", "relation": "calls", "context": "call", "confidence": "EXTRACTED", "source_file": "Vendors.aspx.cs", "source_location": "L344", "weight": 1.0}], "raw_calls": [{"caller_nid": "attendence_vendors_aspx_vendors_page_load", "callee": "Redirect", "is_member_call": true, "source_file": "E:\\attendence\\Vendors.aspx.cs", "source_location": "L17", "receiver": null}, {"caller_nid": "attendence_vendors_aspx_vendors_page_load", "callee": "ToInt32", "is_member_call": true, "source_file": "E:\\attendence\\Vendors.aspx.cs", "source_location": "L22", "receiver": null}, {"caller_nid": "attendence_vendors_aspx_vendors_page_load", "callee": "Write", "is_member_call": true, "source_file": "E:\\attendence\\Vendors.aspx.cs", "source_location": "L25", "receiver": null}, {"caller_nid": "attendence_vendors_aspx_vendors_page_load", "callee": "End", "is_member_call": true, "source_file": "E:\\attendence\\Vendors.aspx.cs", "source_location": "L26", "receiver": null}, {"caller_nid": "attendence_vendors_aspx_vendors_bindgrid", "callee": "Trim", "is_member_call": true, "source_file": "E:\\attendence\\Vendors.aspx.cs", "source_location": "L41", "receiver": null}, {"caller_nid": "attendence_vendors_aspx_vendors_bindgrid", "callee": "IsNullOrEmpty", "is_member_call": true, "source_file": "E:\\attendence\\Vendors.aspx.cs", "source_location": "L51", "receiver": null}, {"caller_nid": "attendence_vendors_aspx_vendors_bindgrid", "callee": "Add", "is_member_call": true, "source_file": "E:\\attendence\\Vendors.aspx.cs", "source_location": "L54", "receiver": null}, {"caller_nid": "attendence_vendors_aspx_vendors_bindgrid", "callee": "ToUpper", "is_member_call": true, "source_file": "E:\\attendence\\Vendors.aspx.cs", "source_location": "L54", "receiver": null}, {"caller_nid": "attendence_vendors_aspx_vendors_bindgrid", "callee": "ExecuteQuery", "is_member_call": true, "source_file": "E:\\attendence\\Vendors.aspx.cs", "source_location": "L59", "receiver": null}, {"caller_nid": "attendence_vendors_aspx_vendors_bindgrid", "callee": "GetAttendanceDBConnection", "is_member_call": true, "source_file": "E:\\attendence\\Vendors.aspx.cs", "source_location": "L59", "receiver": null}, {"caller_nid": "attendence_vendors_aspx_vendors_bindgrid", "callee": "ToArray", "is_member_call": true, "source_file": "E:\\attendence\\Vendors.aspx.cs", "source_location": "L59", "receiver": null}, {"caller_nid": "attendence_vendors_aspx_vendors_bindgrid", "callee": "DataBind", "is_member_call": true, "source_file": "E:\\attendence\\Vendors.aspx.cs", "source_location": "L61", "receiver": null}, {"caller_nid": "attendence_vendors_aspx_vendors_btnsave_click", "callee": "Trim", "is_member_call": true, "source_file": "E:\\attendence\\Vendors.aspx.cs", "source_location": "L76", "receiver": null}, {"caller_nid": "attendence_vendors_aspx_vendors_btnsave_click", "callee": "Trim", "is_member_call": true, "source_file": "E:\\attendence\\Vendors.aspx.cs", "source_location": "L77", "receiver": null}, {"caller_nid": "attendence_vendors_aspx_vendors_btnsave_click", "callee": "Trim", "is_member_call": true, "source_file": "E:\\attendence\\Vendors.aspx.cs", "source_location": "L78", "receiver": null}, {"caller_nid": "attendence_vendors_aspx_vendors_btnsave_click", "callee": "Trim", "is_member_call": true, "source_file": "E:\\attendence\\Vendors.aspx.cs", "source_location": "L79", "receiver": null}, {"caller_nid": "attendence_vendors_aspx_vendors_btnsave_click", "callee": "Trim", "is_member_call": true, "source_file": "E:\\attendence\\Vendors.aspx.cs", "source_location": "L80", "receiver": null}, {"caller_nid": "attendence_vendors_aspx_vendors_btnsave_click", "callee": "IsNullOrEmpty", "is_member_call": true, "source_file": "E:\\attendence\\Vendors.aspx.cs", "source_location": "L83", "receiver": null}, {"caller_nid": "attendence_vendors_aspx_vendors_btnsave_click", "callee": "IsNullOrEmpty", "is_member_call": true, "source_file": "E:\\attendence\\Vendors.aspx.cs", "source_location": "L93", "receiver": null}, {"caller_nid": "attendence_vendors_aspx_vendors_btnsave_click", "callee": "ToInt32", "is_member_call": true, "source_file": "E:\\attendence\\Vendors.aspx.cs", "source_location": "L100", "receiver": null}, {"caller_nid": "attendence_vendors_aspx_vendors_btnsave_click", "callee": "ExecuteScalar", "is_member_call": true, "source_file": "E:\\attendence\\Vendors.aspx.cs", "source_location": "L100", "receiver": null}, {"caller_nid": "attendence_vendors_aspx_vendors_btnsave_click", "callee": "GetAttendanceDBConnection", "is_member_call": true, "source_file": "E:\\attendence\\Vendors.aspx.cs", "source_location": "L100", "receiver": null}, {"caller_nid": "attendence_vendors_aspx_vendors_btnsave_click", "callee": "ToUpper", "is_member_call": true, "source_file": "E:\\attendence\\Vendors.aspx.cs", "source_location": "L101", "receiver": null}, {"caller_nid": "attendence_vendors_aspx_vendors_btnsave_click", "callee": "ToInt32", "is_member_call": true, "source_file": "E:\\attendence\\Vendors.aspx.cs", "source_location": "L110", "receiver": null}, {"caller_nid": "attendence_vendors_aspx_vendors_btnsave_click", "callee": "ExecuteScalar", "is_member_call": true, "source_file": "E:\\attendence\\Vendors.aspx.cs", "source_location": "L110", "receiver": null}, {"caller_nid": "attendence_vendors_aspx_vendors_btnsave_click", "callee": "GetAttendanceDBConnection", "is_member_call": true, "source_file": "E:\\attendence\\Vendors.aspx.cs", "source_location": "L110", "receiver": null}, {"caller_nid": "attendence_vendors_aspx_vendors_btnsave_click", "callee": "ToUpper", "is_member_call": true, "source_file": "E:\\attendence\\Vendors.aspx.cs", "source_location": "L111", "receiver": null}, {"caller_nid": "attendence_vendors_aspx_vendors_btnsave_click", "callee": "IsNullOrEmpty", "is_member_call": true, "source_file": "E:\\attendence\\Vendors.aspx.cs", "source_location": "L123", "receiver": null}, {"caller_nid": "attendence_vendors_aspx_vendors_btnsave_click", "callee": "IsNullOrEmpty", "is_member_call": true, "source_file": "E:\\attendence\\Vendors.aspx.cs", "source_location": "L124", "receiver": null}, {"caller_nid": "attendence_vendors_aspx_vendors_btnsave_click", "callee": "IsNullOrEmpty", "is_member_call": true, "source_file": "E:\\attendence\\Vendors.aspx.cs", "source_location": "L125", "receiver": null}, {"caller_nid": "attendence_vendors_aspx_vendors_btnsave_click", "callee": "IsNullOrEmpty", "is_member_call": true, "source_file": "E:\\attendence\\Vendors.aspx.cs", "source_location": "L126", "receiver": null}, {"caller_nid": "attendence_vendors_aspx_vendors_btnsave_click", "callee": "ExecuteNonQuery", "is_member_call": true, "source_file": "E:\\attendence\\Vendors.aspx.cs", "source_location": "L129", "receiver": null}, {"caller_nid": "attendence_vendors_aspx_vendors_btnsave_click", "callee": "GetAttendanceDBConnection", "is_member_call": true, "source_file": "E:\\attendence\\Vendors.aspx.cs", "source_location": "L129", "receiver": null}, {"caller_nid": "attendence_vendors_aspx_vendors_btnsave_click", "callee": "ToInt32", "is_member_call": true, "source_file": "E:\\attendence\\Vendors.aspx.cs", "source_location": "L135", "receiver": null}, {"caller_nid": "attendence_vendors_aspx_vendors_btnsave_click", "callee": "Trim", "is_member_call": true, "source_file": "E:\\attendence\\Vendors.aspx.cs", "source_location": "L136", "receiver": null}, {"caller_nid": "attendence_vendors_aspx_vendors_btnsave_click", "callee": "ToInt32", "is_member_call": true, "source_file": "E:\\attendence\\Vendors.aspx.cs", "source_location": "L140", "receiver": null}, {"caller_nid": "attendence_vendors_aspx_vendors_btnsave_click", "callee": "ExecuteScalar", "is_member_call": true, "source_file": "E:\\attendence\\Vendors.aspx.cs", "source_location": "L140", "receiver": null}, {"caller_nid": "attendence_vendors_aspx_vendors_btnsave_click", "callee": "GetAttendanceDBConnection", "is_member_call": true, "source_file": "E:\\attendence\\Vendors.aspx.cs", "source_location": "L140", "receiver": null}, {"caller_nid": "attendence_vendors_aspx_vendors_btnsave_click", "callee": "ToUpper", "is_member_call": true, "source_file": "E:\\attendence\\Vendors.aspx.cs", "source_location": "L141", "receiver": null}, {"caller_nid": "attendence_vendors_aspx_vendors_btnsave_click", "callee": "IsNullOrEmpty", "is_member_call": true, "source_file": "E:\\attendence\\Vendors.aspx.cs", "source_location": "L154", "receiver": null}, {"caller_nid": "attendence_vendors_aspx_vendors_btnsave_click", "callee": "IsNullOrEmpty", "is_member_call": true, "source_file": "E:\\attendence\\Vendors.aspx.cs", "source_location": "L155", "receiver": null}, {"caller_nid": "attendence_vendors_aspx_vendors_btnsave_click", "callee": "IsNullOrEmpty", "is_member_call": true, "source_file": "E:\\attendence\\Vendors.aspx.cs", "source_location": "L156", "receiver": null}, {"caller_nid": "attendence_vendors_aspx_vendors_btnsave_click", "callee": "IsNullOrEmpty", "is_member_call": true, "source_file": "E:\\attendence\\Vendors.aspx.cs", "source_location": "L157", "receiver": null}, {"caller_nid": "attendence_vendors_aspx_vendors_btnsave_click", "callee": "ExecuteNonQuery", "is_member_call": true, "source_file": "E:\\attendence\\Vendors.aspx.cs", "source_location": "L161", "receiver": null}, {"caller_nid": "attendence_vendors_aspx_vendors_btnsave_click", "callee": "GetAttendanceDBConnection", "is_member_call": true, "source_file": "E:\\attendence\\Vendors.aspx.cs", "source_location": "L161", "receiver": null}, {"caller_nid": "attendence_vendors_aspx_vendors_gvvendors_rowcommand", "callee": "ToInt32", "is_member_call": true, "source_file": "E:\\attendence\\Vendors.aspx.cs", "source_location": "L184", "receiver": null}, {"caller_nid": "attendence_vendors_aspx_vendors_gvvendors_rowcommand", "callee": "ToInt32", "is_member_call": true, "source_file": "E:\\attendence\\Vendors.aspx.cs", "source_location": "L189", "receiver": null}, {"caller_nid": "attendence_vendors_aspx_vendors_gvvendors_rowcommand", "callee": "ToInt32", "is_member_call": true, "source_file": "E:\\attendence\\Vendors.aspx.cs", "source_location": "L194", "receiver": null}, {"caller_nid": "attendence_vendors_aspx_vendors_gvvendors_rowcommand", "callee": "ToInt32", "is_member_call": true, "source_file": "E:\\attendence\\Vendors.aspx.cs", "source_location": "L199", "receiver": null}, {"caller_nid": "attendence_vendors_aspx_vendors_gvvendors_rowcommand", "callee": "ExecuteScalar", "is_member_call": true, "source_file": "E:\\attendence\\Vendors.aspx.cs", "source_location": "L199", "receiver": null}, {"caller_nid": "attendence_vendors_aspx_vendors_gvvendors_rowcommand", "callee": "GetAttendanceDBConnection", "is_member_call": true, "source_file": "E:\\attendence\\Vendors.aspx.cs", "source_location": "L199", "receiver": null}, {"caller_nid": "attendence_vendors_aspx_vendors_gvvendors_rowcommand", "callee": "ToInt32", "is_member_call": true, "source_file": "E:\\attendence\\Vendors.aspx.cs", "source_location": "L203", "receiver": null}, {"caller_nid": "attendence_vendors_aspx_vendors_gvvendors_rowcommand", "callee": "ExecuteScalar", "is_member_call": true, "source_file": "E:\\attendence\\Vendors.aspx.cs", "source_location": "L203", "receiver": null}, {"caller_nid": "attendence_vendors_aspx_vendors_gvvendors_rowcommand", "callee": "GetAttendanceDBConnection", "is_member_call": true, "source_file": "E:\\attendence\\Vendors.aspx.cs", "source_location": "L203", "receiver": null}, {"caller_nid": "attendence_vendors_aspx_vendors_gvvendors_rowcommand", "callee": "ExecuteNonQuery", "is_member_call": true, "source_file": "E:\\attendence\\Vendors.aspx.cs", "source_location": "L209", "receiver": null}, {"caller_nid": "attendence_vendors_aspx_vendors_gvvendors_rowcommand", "callee": "GetAttendanceDBConnection", "is_member_call": true, "source_file": "E:\\attendence\\Vendors.aspx.cs", "source_location": "L209", "receiver": null}, {"caller_nid": "attendence_vendors_aspx_vendors_gvvendors_rowcommand", "callee": "ExecuteNonQuery", "is_member_call": true, "source_file": "E:\\attendence\\Vendors.aspx.cs", "source_location": "L216", "receiver": null}, {"caller_nid": "attendence_vendors_aspx_vendors_gvvendors_rowcommand", "callee": "GetAttendanceDBConnection", "is_member_call": true, "source_file": "E:\\attendence\\Vendors.aspx.cs", "source_location": "L216", "receiver": null}, {"caller_nid": "attendence_vendors_aspx_vendors_btnhiddenedittrigger_click", "callee": "IsNullOrEmpty", "is_member_call": true, "source_file": "E:\\attendence\\Vendors.aspx.cs", "source_location": "L250", "receiver": null}, {"caller_nid": "attendence_vendors_aspx_vendors_btnhiddenedittrigger_click", "callee": "ToInt32", "is_member_call": true, "source_file": "E:\\attendence\\Vendors.aspx.cs", "source_location": "L252", "receiver": null}, {"caller_nid": "attendence_vendors_aspx_vendors_loadvendorforedit", "callee": "ExecuteQuery", "is_member_call": true, "source_file": "E:\\attendence\\Vendors.aspx.cs", "source_location": "L262", "receiver": null}, {"caller_nid": "attendence_vendors_aspx_vendors_loadvendorforedit", "callee": "GetAttendanceDBConnection", "is_member_call": true, "source_file": "E:\\attendence\\Vendors.aspx.cs", "source_location": "L262", "receiver": null}, {"caller_nid": "attendence_vendors_aspx_vendors_loadvendorforedit", "callee": "ToString", "is_member_call": true, "source_file": "E:\\attendence\\Vendors.aspx.cs", "source_location": "L266", "receiver": null}, {"caller_nid": "attendence_vendors_aspx_vendors_loadvendorforedit", "callee": "ToString", "is_member_call": true, "source_file": "E:\\attendence\\Vendors.aspx.cs", "source_location": "L267", "receiver": null}, {"caller_nid": "attendence_vendors_aspx_vendors_loadvendorforedit", "callee": "ToString", "is_member_call": true, "source_file": "E:\\attendence\\Vendors.aspx.cs", "source_location": "L268", "receiver": null}, {"caller_nid": "attendence_vendors_aspx_vendors_loadvendorforedit", "callee": "ToString", "is_member_call": true, "source_file": "E:\\attendence\\Vendors.aspx.cs", "source_location": "L269", "receiver": null}, {"caller_nid": "attendence_vendors_aspx_vendors_loadvendorforedit", "callee": "ToString", "is_member_call": true, "source_file": "E:\\attendence\\Vendors.aspx.cs", "source_location": "L270", "receiver": null}, {"caller_nid": "attendence_vendors_aspx_vendors_loadvendorforedit", "callee": "ToString", "is_member_call": true, "source_file": "E:\\attendence\\Vendors.aspx.cs", "source_location": "L271", "receiver": null}, {"caller_nid": "attendence_vendors_aspx_vendors_loadvendorforedit", "callee": "ToString", "is_member_call": true, "source_file": "E:\\attendence\\Vendors.aspx.cs", "source_location": "L272", "receiver": null}, {"caller_nid": "attendence_vendors_aspx_vendors_openhistorymodal", "callee": "ExecuteQuery", "is_member_call": true, "source_file": "E:\\attendence\\Vendors.aspx.cs", "source_location": "L301", "receiver": null}, {"caller_nid": "attendence_vendors_aspx_vendors_openhistorymodal", "callee": "GetAttendanceDBConnection", "is_member_call": true, "source_file": "E:\\attendence\\Vendors.aspx.cs", "source_location": "L301", "receiver": null}, {"caller_nid": "attendence_vendors_aspx_vendors_openhistorymodal", "callee": "ToString", "is_member_call": true, "source_file": "E:\\attendence\\Vendors.aspx.cs", "source_location": "L309", "receiver": null}, {"caller_nid": "attendence_vendors_aspx_vendors_openhistorymodal", "callee": "ToString", "is_member_call": true, "source_file": "E:\\attendence\\Vendors.aspx.cs", "source_location": "L310", "receiver": null}, {"caller_nid": "attendence_vendors_aspx_vendors_openhistorymodal", "callee": "ToString", "is_member_call": true, "source_file": "E:\\attendence\\Vendors.aspx.cs", "source_location": "L311", "receiver": null}, {"caller_nid": "attendence_vendors_aspx_vendors_openhistorymodal", "callee": "ToString", "is_member_call": true, "source_file": "E:\\attendence\\Vendors.aspx.cs", "source_location": "L312", "receiver": null}, {"caller_nid": "attendence_vendors_aspx_vendors_openhistorymodal", "callee": "ToString", "is_member_call": true, "source_file": "E:\\attendence\\Vendors.aspx.cs", "source_location": "L313", "receiver": null}, {"caller_nid": "attendence_vendors_aspx_vendors_openhistorymodal", "callee": "ToString", "is_member_call": true, "source_file": "E:\\attendence\\Vendors.aspx.cs", "source_location": "L314", "receiver": null}, {"caller_nid": "attendence_vendors_aspx_vendors_openhistorymodal", "callee": "ToInt32", "is_member_call": true, "source_file": "E:\\attendence\\Vendors.aspx.cs", "source_location": "L315", "receiver": null}, {"caller_nid": "attendence_vendors_aspx_vendors_openhistorymodal", "callee": "ExecuteQuery", "is_member_call": true, "source_file": "E:\\attendence\\Vendors.aspx.cs", "source_location": "L326", "receiver": null}, {"caller_nid": "attendence_vendors_aspx_vendors_openhistorymodal", "callee": "GetAttendanceDBConnection", "is_member_call": true, "source_file": "E:\\attendence\\Vendors.aspx.cs", "source_location": "L326", "receiver": null}, {"caller_nid": "attendence_vendors_aspx_vendors_openhistorymodal", "callee": "Append", "is_member_call": true, "source_file": "E:\\attendence\\Vendors.aspx.cs", "source_location": "L330", "receiver": null}, {"caller_nid": "attendence_vendors_aspx_vendors_openhistorymodal", "callee": "ToString", "is_member_call": true, "source_file": "E:\\attendence\\Vendors.aspx.cs", "source_location": "L336", "receiver": null}, {"caller_nid": "attendence_vendors_aspx_vendors_openhistorymodal", "callee": "ToString", "is_member_call": true, "source_file": "E:\\attendence\\Vendors.aspx.cs", "source_location": "L337", "receiver": null}, {"caller_nid": "attendence_vendors_aspx_vendors_openhistorymodal", "callee": "ToDateTime", "is_member_call": true, "source_file": "E:\\attendence\\Vendors.aspx.cs", "source_location": "L337", "receiver": null}, {"caller_nid": "attendence_vendors_aspx_vendors_openhistorymodal", "callee": "ToString", "is_member_call": true, "source_file": "E:\\attendence\\Vendors.aspx.cs", "source_location": "L338", "receiver": null}, {"caller_nid": "attendence_vendors_aspx_vendors_openhistorymodal", "callee": "ToDateTime", "is_member_call": true, "source_file": "E:\\attendence\\Vendors.aspx.cs", "source_location": "L338", "receiver": null}, {"caller_nid": "attendence_vendors_aspx_vendors_openhistorymodal", "callee": "ToString", "is_member_call": true, "source_file": "E:\\attendence\\Vendors.aspx.cs", "source_location": "L339", "receiver": null}, {"caller_nid": "attendence_vendors_aspx_vendors_openhistorymodal", "callee": "ToInt32", "is_member_call": true, "source_file": "E:\\attendence\\Vendors.aspx.cs", "source_location": "L340", "receiver": null}, {"caller_nid": "attendence_vendors_aspx_vendors_openhistorymodal", "callee": "Append", "is_member_call": true, "source_file": "E:\\attendence\\Vendors.aspx.cs", "source_location": "L342", "receiver": null}, {"caller_nid": "attendence_vendors_aspx_vendors_openhistorymodal", "callee": "Append", "is_member_call": true, "source_file": "E:\\attendence\\Vendors.aspx.cs", "source_location": "L343", "receiver": null}, {"caller_nid": "attendence_vendors_aspx_vendors_openhistorymodal", "callee": "AppendFormat", "is_member_call": true, "source_file": "E:\\attendence\\Vendors.aspx.cs", "source_location": "L344", "receiver": null}, {"caller_nid": "attendence_vendors_aspx_vendors_openhistorymodal", "callee": "AppendFormat", "is_member_call": true, "source_file": "E:\\attendence\\Vendors.aspx.cs", "source_location": "L345", "receiver": null}, {"caller_nid": "attendence_vendors_aspx_vendors_openhistorymodal", "callee": "AppendFormat", "is_member_call": true, "source_file": "E:\\attendence\\Vendors.aspx.cs", "source_location": "L346", "receiver": null}, {"caller_nid": "attendence_vendors_aspx_vendors_openhistorymodal", "callee": "AppendFormat", "is_member_call": true, "source_file": "E:\\attendence\\Vendors.aspx.cs", "source_location": "L347", "receiver": null}, {"caller_nid": "attendence_vendors_aspx_vendors_openhistorymodal", "callee": "AppendFormat", "is_member_call": true, "source_file": "E:\\attendence\\Vendors.aspx.cs", "source_location": "L348", "receiver": null}, {"caller_nid": "attendence_vendors_aspx_vendors_openhistorymodal", "callee": "Append", "is_member_call": true, "source_file": "E:\\attendence\\Vendors.aspx.cs", "source_location": "L349", "receiver": null}, {"caller_nid": "attendence_vendors_aspx_vendors_openhistorymodal", "callee": "Append", "is_member_call": true, "source_file": "E:\\attendence\\Vendors.aspx.cs", "source_location": "L352", "receiver": null}, {"caller_nid": "attendence_vendors_aspx_vendors_openhistorymodal", "callee": "Format", "is_member_call": true, "source_file": "E:\\attendence\\Vendors.aspx.cs", "source_location": "L355", "receiver": null}, {"caller_nid": "attendence_vendors_aspx_vendors_openhistorymodal", "callee": "Format", "is_member_call": true, "source_file": "E:\\attendence\\Vendors.aspx.cs", "source_location": "L358", "receiver": null}, {"caller_nid": "attendence_vendors_aspx_vendors_openhistorymodal", "callee": "ToString", "is_member_call": true, "source_file": "E:\\attendence\\Vendors.aspx.cs", "source_location": "L358", "receiver": null}, {"caller_nid": "attendence_vendors_aspx_vendors_openhistorymodal", "callee": "RegisterStartupScript", "is_member_call": true, "source_file": "E:\\attendence\\Vendors.aspx.cs", "source_location": "L359", "receiver": null}, {"caller_nid": "attendence_vendors_aspx_vendors_openhistorymodal", "callee": "GetType", "is_member_call": true, "source_file": "E:\\attendence\\Vendors.aspx.cs", "source_location": "L359", "receiver": null}, {"caller_nid": "attendence_vendors_aspx_vendors_openhistorymodal", "callee": "ToString", "is_member_call": true, "source_file": "E:\\attendence\\Vendors.aspx.cs", "source_location": "L359", "receiver": null}, {"caller_nid": "attendence_vendors_aspx_vendors_openhistorymodal", "callee": "NewGuid", "is_member_call": true, "source_file": "E:\\attendence\\Vendors.aspx.cs", "source_location": "L359", "receiver": null}, {"caller_nid": "attendence_vendors_aspx_vendors_escapejs", "callee": "IsNullOrEmpty", "is_member_call": true, "source_file": "E:\\attendence\\Vendors.aspx.cs", "source_location": "L369", "receiver": null}, {"caller_nid": "attendence_vendors_aspx_vendors_escapejs", "callee": "Replace", "is_member_call": true, "source_file": "E:\\attendence\\Vendors.aspx.cs", "source_location": "L370", "receiver": null}, {"caller_nid": "attendence_vendors_aspx_vendors_escapejs", "callee": "Replace", "is_member_call": true, "source_file": "E:\\attendence\\Vendors.aspx.cs", "source_location": "L370", "receiver": null}, {"caller_nid": "attendence_vendors_aspx_vendors_escapejs", "callee": "Replace", "is_member_call": true, "source_file": "E:\\attendence\\Vendors.aspx.cs", "source_location": "L370", "receiver": null}, {"caller_nid": "attendence_vendors_aspx_vendors_escapejs", "callee": "Replace", "is_member_call": true, "source_file": "E:\\attendence\\Vendors.aspx.cs", "source_location": "L370", "receiver": null}, {"caller_nid": "attendence_vendors_aspx_vendors_escapejs", "callee": "Replace", "is_member_call": true, "source_file": "E:\\attendence\\Vendors.aspx.cs", "source_location": "L370", "receiver": null}, {"caller_nid": "attendence_vendors_aspx_vendors_generatenextmasterid", "callee": "ExecuteQuery", "is_member_call": true, "source_file": "E:\\attendence\\Vendors.aspx.cs", "source_location": "L380", "receiver": null}, {"caller_nid": "attendence_vendors_aspx_vendors_generatenextmasterid", "callee": "GetAttendanceDBConnection", "is_member_call": true, "source_file": "E:\\attendence\\Vendors.aspx.cs", "source_location": "L380", "receiver": null}, {"caller_nid": "attendence_vendors_aspx_vendors_generatenextmasterid", "callee": "ToString", "is_member_call": true, "source_file": "E:\\attendence\\Vendors.aspx.cs", "source_location": "L383", "receiver": null}, {"caller_nid": "attendence_vendors_aspx_vendors_generatenextmasterid", "callee": "TryParse", "is_member_call": true, "source_file": "E:\\attendence\\Vendors.aspx.cs", "source_location": "L387", "receiver": null}, {"caller_nid": "attendence_vendors_aspx_vendors_generatenextmasterid", "callee": "Substring", "is_member_call": true, "source_file": "E:\\attendence\\Vendors.aspx.cs", "source_location": "L387", "receiver": null}, {"caller_nid": "attendence_vendors_aspx_vendors_generatenextmasterid", "callee": "ToString", "is_member_call": true, "source_file": "E:\\attendence\\Vendors.aspx.cs", "source_location": "L398", "receiver": null}, {"caller_nid": "attendence_vendors_aspx_vendors_showmessage", "callee": "Replace", "is_member_call": true, "source_file": "E:\\attendence\\Vendors.aspx.cs", "source_location": "L411", "receiver": null}, {"caller_nid": "attendence_vendors_aspx_vendors_showmessage", "callee": "Replace", "is_member_call": true, "source_file": "E:\\attendence\\Vendors.aspx.cs", "source_location": "L411", "receiver": null}, {"caller_nid": "attendence_vendors_aspx_vendors_showmessage", "callee": "Replace", "is_member_call": true, "source_file": "E:\\attendence\\Vendors.aspx.cs", "source_location": "L411", "receiver": null}, {"caller_nid": "attendence_vendors_aspx_vendors_showmessage", "callee": "Format", "is_member_call": true, "source_file": "E:\\attendence\\Vendors.aspx.cs", "source_location": "L413", "receiver": null}, {"caller_nid": "attendence_vendors_aspx_vendors_showmessage", "callee": "IsNullOrEmpty", "is_member_call": true, "source_file": "E:\\attendence\\Vendors.aspx.cs", "source_location": "L415", "receiver": null}, {"caller_nid": "attendence_vendors_aspx_vendors_showmessage", "callee": "Format", "is_member_call": true, "source_file": "E:\\attendence\\Vendors.aspx.cs", "source_location": "L417", "receiver": null}, {"caller_nid": "attendence_vendors_aspx_vendors_showmessage", "callee": "RegisterStartupScript", "is_member_call": true, "source_file": "E:\\attendence\\Vendors.aspx.cs", "source_location": "L420", "receiver": null}, {"caller_nid": "attendence_vendors_aspx_vendors_showmessage", "callee": "GetType", "is_member_call": true, "source_file": "E:\\attendence\\Vendors.aspx.cs", "source_location": "L420", "receiver": null}, {"caller_nid": "attendence_vendors_aspx_vendors_showmessage", "callee": "ToString", "is_member_call": true, "source_file": "E:\\attendence\\Vendors.aspx.cs", "source_location": "L420", "receiver": null}, {"caller_nid": "attendence_vendors_aspx_vendors_showmessage", "callee": "NewGuid", "is_member_call": true, "source_file": "E:\\attendence\\Vendors.aspx.cs", "source_location": "L420", "receiver": null}]}